janus/__init__.py
janus/dice.py
janus/main.py
janus_highvar-0.0.2.dist-info/LICENSE.txt
janus_highvar-0.0.2.dist-info/METADATA
janus_highvar-0.0.2.dist-info/WHEEL
janus_highvar-0.0.2.dist-info/entry_points.txt
janus_highvar-0.0.2.dist-info/top_level.txt
janus_highvar-0.0.2.dist-info/RECORD
