Metadata-Version: 2.1
Name: janus-highvar
Version: 0.0.2
Summary: Dungeons and Dragons High Variance Die Roller
Home-page: https://github.com/alexphi314/janus
Author: Alex Philpott
License: UNKNOWN
Platform: UNKNOWN
Requires-Python: >=2.7
Requires-Dist: mock ; python_version<'3.3'
